bigraph/__init__.py
bigraph/algorithms.py
bigraph/bigraph.py
bigraph/evaluation/__init__.py
bigraph/evaluation/evaluation.py
bigraph/preprocessing/__init__.py
bigraph/preprocessing/getAdjacents.py
bigraph/preprocessing/get_adjacents.py
bigraph/preprocessing/importFiles.py
bigraph/preprocessing/import_files.py
bigraph/preprocessing/makeGraph.py
bigraph/preprocessing/make_graph.py
bigraph/preprocessing/pdToList.py
bigraph/preprocessing/pd_to_list.py
evaluation/__init__.py
evaluation/evaluation.py
preprocessing/__init__.py
preprocessing/getAdjacents.py
preprocessing/importFiles.py
preprocessing/makeGraph.py
preprocessing/pdToList.py
bigraph-0.1rc7.dist-info/METADATA
bigraph-0.1rc7.dist-info/WHEEL
bigraph-0.1rc7.dist-info/top_level.txt
bigraph-0.1rc7.dist-info/RECORD
