Metadata-Version: 2.1
Name: bigraph
Version: 0.1rc7
Summary: Python package for link prediction in bipartite graphs and networks
Home-page: https://github.com/bi-graph/bigraph
Author: Soran Ghadri
Author-email: soran.gdr.cs@gmail.com
Maintainer: BiGraph Developers
Maintainer-email: soran.gdr.cs@gmail.com
License: UNKNOWN
Keywords: Networks,Graph Theory,Mathematics,network,graph,bipartite graph,bigraph,link prediction,discrete mathematics,math
Platform: Linux
Platform: Mac OSX
Platform: Windows
Platform: Unix
Classifier: Development Status :: 4 - Beta
Classifier: Intended Audience :: Developers
Classifier: Intended Audience :: Science/Research
Classifier: License :: OSI Approved :: BSD License
Classifier: Operating System :: OS Independent
Classifier: Programming Language :: Python :: 3
Classifier: Programming Language :: Python :: 3.6
Classifier: Programming Language :: Python :: 3.7
Classifier: Programming Language :: Python :: 3.8
Classifier: Topic :: Software Development :: Libraries :: Python Modules
Classifier: Topic :: Scientific/Engineering :: Bio-Informatics
Classifier: Topic :: Scientific/Engineering :: Information Analysis
Classifier: Topic :: Scientific/Engineering :: Mathematics
Classifier: Topic :: Scientific/Engineering :: Physics
Requires-Python: >=3.6
Requires-Dist: matplotlib (>=3.2.0)
Requires-Dist: networkx (>=2.4)
Requires-Dist: numpy (>=1.17.4)
Requires-Dist: pandas (>=0.25.2)
Requires-Dist: scikit-learn (>=0.22)
Requires-Dist: tabulate (>=0.8.7)
Requires-Dist: setuptools (~=51.1.1)
Provides-Extra: developer
Requires-Dist: setuptools (~=51.1.1) ; extra == 'developer'
Provides-Extra: doc
Provides-Extra: extra
Provides-Extra: test
